parallel/legacy.py
parallel/cli/__init__.py
parallel/cli/alias.py
parallel/cli/user.py
parallel/commands/__init__.py
parallel/commands/add_alias.py
parallel/commands/add_users.py
parallel/commands/delete_alias.py
parallel/commands/delete_users.py
parallel/commands/switch_user.py
parallel/utils/alias.py
parallel/utils/io.py
parallel/utils/shell.py
parallel/utils/user.py
paral-0.2.4.dist-info/METADATA
paral-0.2.4.dist-info/WHEEL
paral-0.2.4.dist-info/entry_points.txt
paral-0.2.4.dist-info/RECORD
