Metadata-Version: 2.4
Name: paral
Version: 0.2.4
Summary: An Git User/Credential Switcher
Project-URL: Repository, https://github.com/aoi-cistus/parallel
Project-URL: Issues, https://github.com/aoi-cistus/parallel/issues
License-Expression: MIT
Classifier: Development Status :: 4 - Beta
Classifier: Environment :: Console
Classifier: Intended Audience :: Developers
Classifier: Topic :: Software Development :: Version Control :: Git
Classifier: Topic :: Utilities
Requires-Python: >=3.13
Requires-Dist: pyyaml>=6.0.2
Requires-Dist: questionary>=2.1.0
Requires-Dist: typer>=0.16.0
